pqp-0.3.5.dist-info/METADATA
pqp-0.3.5.dist-info/WHEEL
pqp-0.3.5.dist-info/license_files/LICENSE.txt
pqp/estimation/estimator.py
pqp/estimation/multinomial_estimator.py
pqp/estimation/__init__.py
pqp/fd_demo.py
pqp/data/data.py
pqp/data/domain.py
pqp/data/__init__.py
pqp/.gitignore
pqp/utils/utils.py
pqp/utils/__init__.py
pqp/utils/exceptions.py
pqp/__init__.py
pqp/identification/estimands.py
pqp/identification/graph.py
pqp/identification/__init__.py
pqp/symbols/variable.py
pqp/symbols/relation.py
pqp/symbols/parse.py
pqp/symbols/p.py
pqp/symbols/abstract_math.py
pqp/symbols/event.py
pqp/symbols/__init__.py
pqp/refutation/result.py
pqp/refutation/__init__.py
pqp/pqp.abi3.so
pqp-0.3.5.dist-info/RECORD
