Metadata-Version: 2.1
Name: pqp
Version: 0.3.5
Classifier: License :: OSI Approved :: MIT License
Classifier: Programming Language :: Python
Classifier: Programming Language :: Python :: 3
Requires-Dist: pandas
Requires-Dist: numpy
Requires-Dist: tomli
Requires-Dist: matplotlib; extra == 'dataviz'
Requires-Dist: networkx; extra == 'dataviz'
Requires-Dist: sphinx; extra == 'dev'
Requires-Dist: maturin; extra == 'dev'
Requires-Dist: sphinx-autobuild; extra == 'dev'
Requires-Dist: sphinx_automodapi; extra == 'dev'
Requires-Dist: pytest; extra == 'dev'
Requires-Dist: networkx; extra == 'dev'
Provides-Extra: dataviz
Provides-Extra: dev
License-File: LICENSE.txt
Summary: Subroutines for structural causal modeling
Keywords: causal inference,causal identification
Author: Leo Ware
Requires-Python: >=3.8
Project-URL: Source, https://github.com/leo-ware/capstone
Project-URL: Homepage, https://leo-ware.github.io/capstone/
